{
  "animateLoading": true,
  "borderRadius": "{{appsmith.theme.borderRadius.appBorderRadius}}",
  "bottomRow": 170,
  "dynamicBindingPathList": [
    {
      "key": "truncateButtonColor"
    },
    {
      "key": "fontFamily"
    },
    {
      "key": "borderRadius"
    },
    {
      "key": "text"
    }
  ],
  "dynamicHeight": "AUTO_HEIGHT",
  "dynamicTriggerPathList": [],
  "fontFamily": "{{appsmith.theme.fontFamily.appFont}}",
  "fontSize": "1rem",
  "fontStyle": "BOLD",
  "isLoading": false,
  "isVisible": true,
  "key": "nzrfrrmmo1",
  "leftColumn": 15,
  "maxDynamicHeight": 9000,
  "minDynamicHeight": 4,
  "minWidth": 450,
  "mobileBottomRow": 92,
  "mobileLeftColumn": 15,
  "mobileRightColumn": 31,
  "mobileTopRow": 88,
  "needsErrorInfo": false,
  "originalBottomRow": 170,
  "originalTopRow": 88,
  "overflow": "NONE",
  "parentColumnSpace": 14.234375,
  "parentId": "0",
  "parentRowSpace": 10,
  "renderMode": "CANVAS",
  "responsiveBehavior": "fill",
  "rightColumn": 31,
  "shouldTruncate": false,
  "text": "{{ getMembros.data?.data?.[0]?.planos_de_trabalho }}\n",
  "textAlign": "LEFT",
  "textColor": "#231F20",
  "topRow": 88,
  "truncateButtonColor": "{{appsmith.theme.colors.primaryColor}}",
  "type": "TEXT_WIDGET",
  "version": 1,
  "widgetId": "3yx5rqoz73",
  "widgetName": "Text11"
}