{
  "gitSyncId": "68375c2c56cad916c8fc38e2_8d38f649-34b6-4893-93bf-788bb5336576",
  "id": "Financeiro_GraficoProjetoTipo.porTipo",
  "pluginId": "js-plugin",
  "pluginType": "JS",
  "unpublishedAction": {
    "actionConfiguration": {
      "encodeParamsToggle": true,
      "jsArguments": [],
      "paginationType": "NONE",
      "timeoutInMillisecond": 10000
    },
    "collectionId": "Financeiro_GraficoProjetoTipo",
    "confirmBeforeExecute": false,
    "datasource": {
      "isAutoGenerated": false,
      "name": "UNUSED_DATASOURCE",
      "pluginId": "js-plugin"
    },
    "dynamicBindingPathList": [
      {
        "key": "body"
      }
    ],
    "fullyQualifiedName": "GraficoProjetoTipo.porTipo",
    "name": "porTipo",
    "pageId": "Financeiro",
    "runBehaviour": "ON_PAGE_LOAD",
    "userSetOnLoad": true
  }
}