{
  "animateLoading": true,
  "borderRadius": "{{appsmith.theme.borderRadius.appBorderRadius}}",
  "bottomRow": 13,
  "boxShadow": "none",
  "buttonColor": "#1d4ed8",
  "buttonStyle": "PRIMARY",
  "buttonVariant": "SECONDARY",
  "disabledWhenInvalid": false,
  "dynamicBindingPathList": [
    {
      "key": "borderRadius"
    }
  ],
  "dynamicPropertyPathList": [],
  "dynamicTriggerPathList": [
    {
      "key": "onClick"
    }
  ],
  "isDefaultClickDisabled": true,
  "isDisabled": false,
  "isLoading": false,
  "isVisible": true,
  "key": "qlp3bheqt4",
  "leftColumn": 15,
  "minWidth": 120,
  "mobileBottomRow": 22,
  "mobileLeftColumn": 31,
  "mobileRightColumn": 47,
  "mobileTopRow": 18,
  "needsErrorInfo": false,
  "onClick": "{{showModal(EditarBolsa.name);}}",
  "originalBottomRow": 24,
  "originalTopRow": 20,
  "parentId": "ophue7qy6f",
  "placement": "CENTER",
  "recaptchaType": "V3",
  "renderMode": "CANVAS",
  "resetFormOnClick": false,
  "responsiveBehavior": "hug",
  "rightColumn": 31,
  "text": "Voltar",
  "topRow": 9,
  "type": "BUTTON_WIDGET",
  "version": 1,
  "widgetId": "t0pldlvs8d",
  "widgetName": "voltar"
}