{
  "animateLoading": true,
  "borderRadius": "{{appsmith.theme.borderRadius.appBorderRadius}}",
  "bottomRow": 23,
  "boxShadow": "none",
  "buttonColor": "{{appsmith.theme.colors.primaryColor}}",
  "buttonStyle": "PRIMARY_BUTTON",
  "buttonVariant": "SECONDARY",
  "disabledWhenInvalid": false,
  "dynamicBindingPathList": [
    {
      "key": "buttonColor"
    },
    {
      "key": "borderRadius"
    }
  ],
  "dynamicTriggerPathList": [
    {
      "key": "onClick"
    }
  ],
  "iconAlign": "left",
  "iconName": "add",
  "isDefaultClickDisabled": true,
  "isDisabled": false,
  "isLoading": false,
  "isVisible": true,
  "key": "erg03e2uo6",
  "leftColumn": 54,
  "minWidth": 120,
  "mobileBottomRow": 22,
  "mobileLeftColumn": 47,
  "mobileRightColumn": 63,
  "mobileTopRow": 18,
  "needsErrorInfo": false,
  "onClick": "{{showModal(Modal1.name);}}",
  "originalBottomRow": 20,
  "originalTopRow": 16,
  "parentId": "2u9n92bl3l",
  "placement": "CENTER",
  "recaptchaType": "V3",
  "renderMode": "CANVAS",
  "resetFormOnClick": false,
  "responsiveBehavior": "hug",
  "rightColumn": 62,
  "text": "Adicionar",
  "topRow": 19,
  "type": "BUTTON_WIDGET",
  "version": 1,
  "widgetId": "jxpsdbi90d",
  "widgetName": "Button16Copy"
}