{
  "gitSyncId": "68375c2c56cad916c8fc38e2_7ef51ff3-cbc1-4248-8bdc-68e85dc13ac1",
  "id": "Financeiro_abrirArquivo.abrir",
  "pluginId": "js-plugin",
  "pluginType": "JS",
  "unpublishedAction": {
    "actionConfiguration": {
      "encodeParamsToggle": true,
      "jsArguments": [
        {
          "name": "url"
        }
      ],
      "paginationType": "NONE",
      "timeoutInMillisecond": 10000
    },
    "collectionId": "Financeiro_abrirArquivo",
    "confirmBeforeExecute": false,
    "datasource": {
      "isAutoGenerated": false,
      "name": "UNUSED_DATASOURCE",
      "pluginId": "js-plugin"
    },
    "dynamicBindingPathList": [
      {
        "key": "body"
      }
    ],
    "fullyQualifiedName": "abrirArquivo.abrir",
    "name": "abrir",
    "pageId": "Financeiro",
    "runBehaviour": "MANUAL",
    "userSetOnLoad": false
  }
}